osf_downloader/__init__.py
osf_downloader/cli.py
osf_downloader/download.py
osf_downloader-0.1.0.dist-info/licenses/LICENSE
osf_downloader-0.1.0.dist-info/METADATA
osf_downloader-0.1.0.dist-info/WHEEL
osf_downloader-0.1.0.dist-info/entry_points.txt
osf_downloader-0.1.0.dist-info/top_level.txt
osf_downloader-0.1.0.dist-info/RECORD
