Metadata-Version: 2.4
Name: osf-downloader
Version: 0.1.0
Summary: Download files from osf.io
Author: Ahmet Selim Canakci
License: MIT
Project-URL: Homepage, https://github.com/aselimc/osf-downloader
Keywords: osf,downloader,research
Requires-Python: >=3.9
License-File: LICENSE
Requires-Dist: requests
Requires-Dist: typer[all]
Requires-Dist: tqdm
Requires-Dist: rich
Provides-Extra: dev
Requires-Dist: ruff; extra == "dev"
Requires-Dist: black; extra == "dev"
Requires-Dist: pytest; extra == "dev"
Dynamic: license-file
